deferred_import/__init__.py
deferred_import/_core.py
deferred_import-0.1.0.dist-info/LICENSE
deferred_import-0.1.0.dist-info/WHEEL
deferred_import-0.1.0.dist-info/METADATA
deferred_import-0.1.0.dist-info/RECORD
