Metadata-Version: 2.1
Name: deferred-import
Version: 0.1.0
Summary: Lazy import and install on demand Python packages.
Home-page: https://github.com/orsinium-labs/deferred-import
License: MIT
Keywords: import,defer,install,pip,lazy
Author: Gram
Author-email: gram@orsinium.dev
Requires-Python: >=3.6
Classifier: Development Status :: 5 - Production/Stable
Classifier: Intended Audience :: Developers
Classifier: License :: OSI Approved :: MIT License
Classifier: Programming Language :: Python
Classifier: Topic :: Software Development
Requires-Dist: isort ; extra == "dev"
Requires-Dist: mypy ; extra == "dev"
Requires-Dist: pytest ; extra == "dev"
Requires-Dist: flake8 ; extra == "dev"
Provides-Extra: dev
